vcc_kms_client/__init__.py
vcc_kms_client/change_state_kms_key_repository.py
vcc_kms_client/create_kms_key_repository.py
vcc_kms_client/create_kms_key_service.py
vcc_kms_client/decrypt_repository.py
vcc_kms_client/decrypt_service.py
vcc_kms_client/decrypt_with_data_key_pair_service.py
vcc_kms_client/decrypt_with_data_key_service.py
vcc_kms_client/delete_alias_key_service.py
vcc_kms_client/delete_kms_key_service.py
vcc_kms_client/describe_kms_key_service.py
vcc_kms_client/disable_kms_key_service.py
vcc_kms_client/enable_kms_key_service.py
vcc_kms_client/encrypt_repository.py
vcc_kms_client/encrypt_service.py
vcc_kms_client/encrypt_with_data_key_pair_service.py
vcc_kms_client/encrypt_with_data_key_service.py
vcc_kms_client/generate_data_key_pair_service.py
vcc_kms_client/generate_data_key_repository.py
vcc_kms_client/generate_data_key_service.py
vcc_kms_client/get_kms_key_repository.py
vcc_kms_client/handler_response_http.py
vcc_kms_client/kms_client.py
vcc_kms_client/list_kms_key_by_alias_service.py
vcc_kms_client/list_kms_key_repository.py
vcc_kms_client/list_kms_key_service.py
vcc_kms_client/manage_alias_key_repository.py
vcc_kms_client/sign_repository.py
vcc_kms_client/sign_service.py
vcc_kms_client/update_alias_key_service.py
vcc_kms_client/update_description_key_repository.py
vcc_kms_client/update_description_key_service.py
vcc_kms_client/verify_repository.py
vcc_kms_client/verify_service.py
vcc_kms_client/auth/__init__.py
vcc_kms_client/auth/kms_credentials.py
vcc_kms_client/constants/__init__.py
vcc_kms_client/constants/constants.py
vcc_kms_client/dtos/__init__.py
vcc_kms_client/dtos/alias_key_dto.py
vcc_kms_client/dtos/change_state_dto.py
vcc_kms_client/dtos/decrypt_dto.py
vcc_kms_client/dtos/description_key_dto.py
vcc_kms_client/dtos/encrypt_dto.py
vcc_kms_client/dtos/generate_data_key_dto.py
vcc_kms_client/dtos/kms_key_dto.py
vcc_kms_client/dtos/sign_dto.py
vcc_kms_client/dtos/verify_dto.py
vcc_kms_client/https/__init__.py
vcc_kms_client-0.0.1.dist-info/METADATA
vcc_kms_client-0.0.1.dist-info/WHEEL
vcc_kms_client-0.0.1.dist-info/licenses/LICENSE
vcc_kms_client-0.0.1.dist-info/RECORD
