Metadata-Version: 2.1
Name: vcc_kms_client
Version: 0.0.1
Summary: KMS is a key management system for data encryption, decryption, signing and verification
Author-email: cuongpm <cuongphammanh@tech.admicro.vn>
License-File: LICENSE
Classifier: License :: OSI Approved :: MIT License
Classifier: Operating System :: OS Independent
Classifier: Programming Language :: Python :: 3
Requires-Python: >=3.8
